alu_8bit.v
// 8-Bit Arithmetic Logic Unit (ALU)
// Module Name: alu_8bit
// Description: Implements 8 ALU operations based on a 3-bit selector.

module alu_8bit (
    input  wire [7:0] A,          // 8-bit input A
    input  wire [7:0] B,          // 8-bit input B
    input  wire [2:0] ALU_Sel,    // 3-bit operation selector
    output reg  [7:0] ALU_Out,    // 8-bit ALU output
    output reg        CarryOut,   // Carry out flag (for addition/subtraction)
    output wire       Zero        // Zero flag (1 if ALU_Out is 0)
);

    // Temporary 9-bit register to capture addition carry / subtraction borrow
    reg [8:0] temp_res;

    // Zero Flag: Set to 1 if the output is all zeros
    assign Zero = (ALU_Out == 8'b0);

    always @(*) begin
        // Defaults to avoid latch inference
        CarryOut = 1'b0;
        temp_res = 9'b0;
        
        case (ALU_Sel)
            3'b000: begin // ADD: Addition
                temp_res = A + B;
                ALU_Out  = temp_res[7:0];
                CarryOut = temp_res[8];
            end
            
            3'b001: begin // SUB: Subtraction
                temp_res = A - B;
                ALU_Out  = temp_res[7:0];
                CarryOut = temp_res[8]; // Borrow out (indicates underflow)
            end
            
            3'b010: begin // AND: Bitwise AND
                ALU_Out  = A & B;
            end
            
            3'b011: begin // OR: Bitwise OR
                ALU_Out  = A | B;
            end
            
            3'b100: begin // XOR: Bitwise XOR
                ALU_Out  = A ^ B;
            end
            
            3'b101: begin // NOT: Bitwise NOT of input A
                ALU_Out  = ~A;
            end
            
            3'b110: begin // SLL: Logical Shift Left A by B[2:0] positions
                ALU_Out  = A << B[2:0];
            end
            
            3'b111: begin // SRL: Logical Shift Right A by B[2:0] positions
                ALU_Out  = A >> B[2:0];
            end
            
            default: begin
                ALU_Out  = 8'b0;
                CarryOut = 1'b0;
            end
        endcase
    end

endmodule

Assignment-1/alu_8bit_tb.v
`timescale 1ns / 1ps

module alu_8bit_tb;

    // Inputs (registers in testbench)
    reg [7:0] A;
    reg [7:0] B;
    reg [2:0] ALU_Sel;

    // Outputs (wires in testbench)
    wire [7:0] ALU_Out;
    wire CarryOut;
    wire Zero;

    // Instantiate the Unit Under Test (UUT)
    alu_8bit uut (
        .A(A), 
        .B(B), 
        .ALU_Sel(ALU_Sel), 
        .ALU_Out(ALU_Out), 
        .CarryOut(CarryOut), 
        .Zero(Zero)
    );

    initial begin
        // Enable waveform dump
        $dumpfile("alu_8bit.vcd");
        $dumpvars(0, alu_8bit_tb);
        
        $display("==========================================================================");
        $display("                   8-BIT ALU TESTBENCH START                              ");
        $display("==========================================================================");
        $display("Time(ns) | ALU_Sel |  A (Hex) |  B (Hex) | ALU_Out (Hex) | CarryOut | Zero");
        $display("---------+---------+-----------+-----------+---------------+----------+-----");

        // --- Test Case 1: ADD without carry ---
        A = 8'h12; B = 8'h34; ALU_Sel = 3'b000;
        #10;
        $display("%8d |   ADD   |    %2h     |    %2h     |      %2h       |    %b     |  %b", $time, A, B, ALU_Out, CarryOut, Zero);

        // --- Test Case 2: ADD with carry ---
        A = 8'hFF; B = 8'h01; ALU_Sel = 3'b000;
        #10;
        $display("%8d |   ADD   |    %2h     |    %2h     |      %2h       |    %b     |  %b", $time, A, B, ALU_Out, CarryOut, Zero);

        // --- Test Case 3: SUB without borrow ---
        A = 8'h50; B = 8'h20; ALU_Sel = 3'b001;
        #10;
        $display("%8d |   SUB   |    %2h     |    %2h     |      %2h       |    %b     |  %b", $time, A, B, ALU_Out, CarryOut, Zero);

        // --- Test Case 4: SUB with borrow (underflow) ---
        A = 8'h10; B = 8'h20; ALU_Sel = 3'b001;
        #10;
        $display("%8d |   SUB   |    %2h     |    %2h     |      %2h       |    %b     |  %b", $time, A, B, ALU_Out, CarryOut, Zero);

        // --- Test Case 5: AND ---
        A = 8'hAA; B = 8'h55; ALU_Sel = 3'b010;
        #10;
        $display("%8d |   AND   |    %2h     |    %2h     |      %2h       |    %b     |  %b", $time, A, B, ALU_Out, CarryOut, Zero);

        // --- Test Case 6: OR ---
        A = 8'hAA; B = 8'h55; ALU_Sel = 3'b011;
        #10;
        $display("%8d |   OR    |    %2h     |    %2h     |      %2h       |    %b     |  %b", $time, A, B, ALU_Out, CarryOut, Zero);

        // --- Test Case 7: XOR ---
        A = 8'hF0; B = 8'h0F; ALU_Sel = 3'b100;
        #10;
        $display("%8d |   XOR   |    %2h     |    %2h     |      %2h       |    %b     |  %b", $time, A, B, ALU_Out, CarryOut, Zero);

        // --- Test Case 8: NOT ---
        A = 8'h0F; B = 8'h00; ALU_Sel = 3'b101;
        #10;
        $display("%8d |   NOT   |    %2h     |    %2h     |      %2h       |    %b     |  %b", $time, A, B, ALU_Out, CarryOut, Zero);

        // --- Test Case 9: SLL by 1 ---
        A = 8'h01; B = 8'h01; ALU_Sel = 3'b110;
        #10;
        $display("%8d |   SLL   |    %2h     |    %2h     |      %2h       |    %b     |  %b", $time, A, B, ALU_Out, CarryOut, Zero);

        // --- Test Case 10: SLL by 4 ---
        A = 8'h0F; B = 8'h04; ALU_Sel = 3'b110;
        #10;
        $display("%8d |   SLL   |    %2h     |    %2h     |      %2h       |    %b     |  %b", $time, A, B, ALU_Out, CarryOut, Zero);

        // --- Test Case 11: SRL by 1 ---
        A = 8'h80; B = 8'h01; ALU_Sel = 3'b111;
        #10;
        $display("%8d |   SRL   |    %2h     |    %2h     |      %2h       |    %b     |  %b", $time, A, B, ALU_Out, CarryOut, Zero);

        // --- Test Case 12: SRL by 4 ---
        A = 8'hF0; B = 8'h04; ALU_Sel = 3'b111;
        #10;
        $display("%8d |   SRL   |    %2h     |    %2h     |      %2h       |    %b     |  %b", $time, A, B, ALU_Out, CarryOut, Zero);

        // --- Test Case 13: Zero Flag Verification ---
        A = 8'hFF; B = 8'hFF; ALU_Sel = 3'b001; // Subtraction resulting in zero
        #10;
        $display("%8d |   SUB   |    %2h     |    %2h     |      %2h       |    %b     |  %b", $time, A, B, ALU_Out, CarryOut, Zero);

        $display("==========================================================================");
        $display("                   8-BIT ALU TESTBENCH COMPLETED                          ");
        $display("==========================================================================");
        $finish;
    end
      
endmodule

alu_8bit.vcd
$date
	Sat Jun 27 23:12:38 2026
$end
$version
	Icarus Verilog
$end
$timescale
	1ps
$end
$scope module alu_8bit_tb $end
$var wire 1 ! Zero $end
$var wire 1 " CarryOut $end
$var wire 8 # ALU_Out [7:0] $end
$var reg 8 $ A [7:0] $end
$var reg 3 % ALU_Sel [2:0] $end
$var reg 8 & B [7:0] $end
$scope module uut $end
$var wire 8 ' A [7:0] $end
$var wire 3 ( ALU_Sel [2:0] $end
$var wire 8 ) B [7:0] $end
$var wire 1 ! Zero $end
$var reg 8 * ALU_Out [7:0] $end
$var reg 1 " CarryOut $end
$var reg 9 + temp_res [8:0] $end
$upscope $end
$upscope $end
$enddefinitions $end
$comment Show the parameter values. $end
$dumpall
$end
#0
$dumpvars
b1000110 +
b1000110 *
b110100 )
b0 (
b10010 '
b110100 &
b0 %
b10010 $
b1000110 #
0"
0!
$end
#10000
1"
1!
b0 #
b0 *
b100000000 +
b1 &
b1 )
b11111111 $
b11111111 '
#20000
0!
b110000 #
b110000 *
b110000 +
0"
b1 %
b1 (
b100000 &
b100000 )
b1010000 $
b1010000 '
#30000
1"
b11110000 #
b11110000 *
b111110000 +
b10000 $
b10000 '
#40000
1!
b0 #
b0 *
b0 +
0"
b10 %
b10 (
b1010101 &
b1010101 )
b10101010 $
b10101010 '
#50000
0!
b11111111 #
b11111111 *
b11 %
b11 (
#60000
b100 %
b100 (
b1111 &
b1111 )
b11110000 $
b11110000 '
#70000
b11110000 #
b11110000 *
b101 %
b101 (
b0 &
b0 )
b1111 $
b1111 '
#80000
b10 #
b10 *
b110 %
b110 (
b1 &
b1 )
b1 $
b1 '
#90000
b11110000 #
b11110000 *
b100 &
b100 )
b1111 $
b1111 '
#100000
b1000000 #
b1000000 *
b111 %
b111 (
b1 &
b1 )
b10000000 $
b10000000 '
#110000
b1111 #
b1111 *
b100 &
b100 )
b11110000 $
b11110000 '
#120000
1!
b0 #
b0 *
b1 %
b1 (
b11111111 &
b11111111 )
b11111111 $
b11111111 '
